yuzu/__init__.py
yuzu/models.py
yuzu/naive_ism.py
yuzu/precompute.py
yuzu/utils.py
yuzu/yuzu_ism.py
yuzu_ism-0.0.1.dist-info/LICENSE
yuzu_ism-0.0.1.dist-info/METADATA
yuzu_ism-0.0.1.dist-info/WHEEL
yuzu_ism-0.0.1.dist-info/top_level.txt
yuzu_ism-0.0.1.dist-info/RECORD
