Metadata-Version: 2.1
Name: yuzu-ism
Version: 0.0.1
Summary: yuzu implements a compressed-sensing based approach for speeding up saliency calculations.
Home-page: http://pypi.python.org/pypi/yuzu-ism/
Author: Jacob Schreiber
Author-email: jmschreiber91@gmail.com
License: LICENSE.txt
Platform: UNKNOWN
Requires-Dist: numpy (>=1.14.2)
Requires-Dist: torch (>=1.9.0)
